reusable_code/__init__.py
reusable_code/measure_processing_time.py
reusable_code/process_document.py
reusable_code_for_document_ai-0.1.1.dist-info/METADATA
reusable_code_for_document_ai-0.1.1.dist-info/WHEEL
reusable_code_for_document_ai-0.1.1.dist-info/top_level.txt
reusable_code_for_document_ai-0.1.1.dist-info/RECORD
