Metadata-Version: 2.1
Name: reusable-code-for-document-ai
Version: 0.1.1
Summary: Reusable code for Google Document-AI services
Home-page: https://github.com/Muazzeem/reusable-doc-ai-package
Author: Muazzem
Author-email: muazzem.mamun@gmail.com.com
Classifier: Programming Language :: Python :: 3
Classifier: License :: OSI Approved :: MIT License
Classifier: Operating System :: OS Independent
Requires-Python: >=3.7
